locnus/__init__.py
locnus/admin.py
locnus/apps.py
locnus/forms.py
locnus/models.py
locnus/urls.py
locnus/views.py
locnus/management/commands/import_server_urls.py
locnus/migrations/0001_initial.py
locnus/migrations/0002_alter_timeline_tag.py
locnus/migrations/__init__.py
locnus/static/.gitignore
locnus/templates/_base.html
locnus/templates/account_detail.html
locnus/templates/account_list.html
locnus/templates/create_account.html
locnus/templates/create_server.html
locnus/templates/create_toot.html
locnus/templates/home.html
locnus/templates/server_list.html
locnus/templates/timeline.html
locnus/templates/timeline_partial.html
locnus-0.0.2.dist-info/WHEEL
locnus-0.0.2.dist-info/METADATA
locnus-0.0.2.dist-info/RECORD
