Metadata-Version: 2.1
Name: locnus
Version: 0.0.2
Summary: Giant sloth
Keywords: Django,Mastodon,ActivityPub,Fediverse
Author-email: Jochen Wersdörfer <jochen@wersdoerfer.de>
Requires-Python: >=3.10
Classifier: Environment :: Web Environment
Classifier: Framework :: Django
Classifier: Framework :: Django :: 4.2
Classifier: Intended Audience :: Developers
Classifier: License :: OSI Approved :: BSD License
Classifier: Topic :: Internet
Classifier: Development Status :: 3 - Alpha
Classifier: Environment :: Web Environment
Classifier: License :: OSI Approved :: MIT License
Classifier: Programming Language :: Python :: 3 :: Only
Classifier: Programming Language :: Python :: 3.11
Classifier: Topic :: Internet :: WWW/HTTP
Classifier: Topic :: Internet :: WWW/HTTP :: Dynamic Content
Requires-Dist: crispy-bootstrap5
Requires-Dist: django
Requires-Dist: django-htmx
Requires-Dist: Mastodon.py
Requires-Dist: whitenoise
Requires-Dist: black ; extra == "dev"
Requires-Dist: flake8 ; extra == "dev"
Requires-Dist: django_extensions ; extra == "dev"
Requires-Dist: django-stubs ; extra == "dev"
Requires-Dist: isort ; extra == "dev"
Requires-Dist: jupyterlab ; extra == "dev"
Requires-Dist: jupyter-server<2.0.0 ; extra == "dev"
Requires-Dist: rich ; extra == "dev"
Requires-Dist: tox ; extra == "dev"
Requires-Dist: typer ; extra == "dev"
Requires-Dist: furo ; extra == "doc"
Requires-Dist: pytest >= 6 ; extra == "test"
Requires-Dist: pytest-cov >= 3 ; extra == "test"
Requires-Dist: pytest-django ; extra == "test"
Requires-Dist: pytest-mock ; extra == "test"
Requires-Dist: pytest-randomly ; extra == "test"
Project-URL: Documentation, https://github.com/ephes/pytest-course
Project-URL: Source, https://github.com/ephes/pytest-course
Provides-Extra: dev
Provides-Extra: doc
Provides-Extra: test
